<annotation>
	<folder>train</folder>
	<filename>frame21367.jpg</filename>
	<path>/home/algoscale/Desktop/ambuj_data/train/frame21367.jpg</path>
	<source>
		<database>Unknown</database>
	</source>
	<size>
		<width>1280</width>
		<height>720</height>
		<depth>3</depth>
	</size>
	<segmented>0</segmented>
	<object>
		<name>spike</name>
		<pose>Unspecified</pose>
		<truncated>0</truncated>
		<difficult>0</difficult>
		<bndbox>
			<xmin>622</xmin>
			<ymin>79</ymin>
			<xmax>856</xmax>
			<ymax>317</ymax>
		</bndbox>
	</object>
	<object>
		<name>tom</name>
		<pose>Unspecified</pose>
		<truncated>0</truncated>
		<difficult>0</difficult>
		<bndbox>
			<xmin>388</xmin>
			<ymin>65</ymin>
			<xmax>589</xmax>
			<ymax>246</ymax>
		</bndbox>
	</object>
</annotation>
